HISTORY.txt
README.txt
ez_setup.py
setup.cfg
setup.py
src/ClueMapperThemer.egg-info/PKG-INFO
src/ClueMapperThemer.egg-info/SOURCES.txt
src/ClueMapperThemer.egg-info/dependency_links.txt
src/ClueMapperThemer.egg-info/namespace_packages.txt
src/ClueMapperThemer.egg-info/requires.txt
src/ClueMapperThemer.egg-info/top_level.txt
src/ClueMapperThemer.egg-info/zip-safe
src/clue/__init__.py
src/clue/themer/__init__.py
src/clue/themer/cluemapperthemer.txt
src/clue/themer/tests.py
src/clue/themer/theme.py
src/clue/themer/defaulttheme/rules/rules.xml
src/clue/themer/defaulttheme/rules/standardrules.xml
src/clue/themer/defaulttheme/static/favicon.ico
src/clue/themer/defaulttheme/static/logo.jpg
src/clue/themer/defaulttheme/static/prototype.js
src/clue/themer/defaulttheme/static/theme.css
src/clue/themer/defaulttheme/static/theme.html