Metadata-Version: 1.0
Name: ClueMapperThemer
Version: 0.6
Summary: Theming plugin for ClueMapper+trac.
Home-page: http://projects.serverzen.com/pm/p/cluemapper
Author: Rocky Burt
Author-email: rocky@serverzen.com
License: BSD
Platform: UNKNOWN
Classifier: Programming Language :: Python
Classifier: Topic :: Software Development :: Libraries :: Python Modules
